AUTHORS
ChangeLog
LICENSE
MANIFEST.in
README.rst
requirements.txt
setup.cfg
setup.py
test-requirements.txt
tox.ini
bosi/__init__.py
bosi/bosi.py
bosi/hooks.py
bosi.egg-info/PKG-INFO
bosi.egg-info/SOURCES.txt
bosi.egg-info/dependency_links.txt
bosi.egg-info/entry_points.txt
bosi.egg-info/not-zip-safe
bosi.egg-info/pbr.json
bosi.egg-info/requires.txt
bosi.egg-info/top_level.txt
bosi/lib/__init__.py
bosi/lib/bridge.py
bosi/lib/constants.py
bosi/lib/environment.py
bosi/lib/helper.py
bosi/lib/membership_rule.py
bosi/lib/node.py
bosi/lib/rest.py
bosi/lib/util.py
bosi/rhosp_resources/README
bosi/rhosp_resources/master/ivs/README
bosi/rhosp_resources/master/ivs/clear_bcf_ssl_certs.sh
bosi/rhosp_resources/master/ivs/customize.sh
bosi/rhosp_resources/master/ivs/impl_ifcfg.py
bosi/rhosp_resources/master/ivs/pre_request.sh
bosi/rhosp_resources/master/ivs/startup.sh
bosi/rhosp_resources/master/yamls/bigswitch-config-p.yaml
bosi/rhosp_resources/master/yamls/bigswitch-config-pv.yaml
bosi/rhosp_resources/master/yamls/bsn-patch.txt
bosi/rhosp_resources/master/yamls/ceph-storage.yaml
bosi/rhosp_resources/master/yamls/cinder-storage.yaml
bosi/rhosp_resources/master/yamls/compute.yaml_ivs
bosi/rhosp_resources/master/yamls/compute.yaml_ovs
bosi/rhosp_resources/master/yamls/controller.yaml
bosi/rhosp_resources/master/yamls/local_registry_images_bigswitch.yaml
bosi/rhosp_resources/master/yamls/network-environment-bcf.yaml
bosi/rhosp_resources/master/yamls/neutron-bigswitch-agent.yaml
bosi/rhosp_resources/master/yamls/node-info.yaml
bosi/rhosp_resources/master/yamls/overcloud_images_bigswitch.yaml
bosi/rhosp_resources/master/yamls/swift-storage.yaml
bosi/rhosp_resources/master/yamls/yaml_validate.py
bosi/rhosp_resources/origin/stable/liberty
bosi/rhosp_resources/origin/stable/queens
bosi/rhosp_resources/origin/stable/mitaka/build_scripts/rhosp_nfvswitch_packager.sh
bosi/rhosp_resources/origin/stable/mitaka/build_scripts/rhosp_packager.sh
bosi/rhosp_resources/origin/stable/mitaka/ivs/README
bosi/rhosp_resources/origin/stable/mitaka/ivs/customize.sh
bosi/rhosp_resources/origin/stable/mitaka/ivs/pre_request.sh
bosi/rhosp_resources/origin/stable/mitaka/ivs/startup.sh
